logstash_formatter/__init__.py
logstash_formatter-0.5.16.dist-info/DESCRIPTION.rst
logstash_formatter-0.5.16.dist-info/METADATA
logstash_formatter-0.5.16.dist-info/RECORD
logstash_formatter-0.5.16.dist-info/WHEEL
logstash_formatter-0.5.16.dist-info/metadata.json
logstash_formatter-0.5.16.dist-info/top_level.txt
