Metadata-Version: 2.0
Name: logstash-formatter
Version: 0.5.16
Summary: JSON formatter meant for logstash
Home-page: https://github.com/exoscale/python-logstash-formatter
Author: Pierre-Yves Ritschard
Author-email: pierre-yves.ritschard@exoscale.ch
License: MIT, see LICENSE file
Platform: UNKNOWN
Classifier: Development Status :: 5 - Production/Stable
Classifier: Intended Audience :: Developers
Classifier: License :: OSI Approved :: MIT License
Classifier: Natural Language :: English
Classifier: Programming Language :: Python
Classifier: Programming Language :: Python :: 3
